django_super_tables/__init__.py
django_super_tables-0.0.0.dist-info/LICENSE
django_super_tables-0.0.0.dist-info/METADATA
django_super_tables-0.0.0.dist-info/WHEEL
django_super_tables-0.0.0.dist-info/RECORD
